{
    "type": "intro_dialogue",
    "desc" : "타입은 꼭 포함해야 한다.",
    "items": {
        "init" : [
            {
                "type" : "narration",
                "text" : "당신은 살갖에 느껴지는 건조한 모래바람에 눈을 뜹니다. (클릭해서 넘기세요)"
            },
            {
                "type" : "narration",
                "text" : "당신은 며칠째 이 황무지를 횡단하고 있었습니다. 어떤 도시를 찾기 위해서죠."
            },
            {
                "type" : "narration",
                "text" : "이유는 간단합니다. 원래 물건을 되찾기 위해서 노예 사냥꾼들이 분주히 쫓아오고 있을 거거든요! 그리고 이 황무지에는 숨을 곳이 마땅히 없습니다. 그나마 그 버려진 도시에서 희망을 찾을 수 있을 것 같네요."
            },
            {
                "type" : "narration",
                "text" : "도시의 존재는 옆에 있는 소녀가 알려줬습니다. 그녀는 노예 캠프를 탈출할 때 당신을 따라온 동료입니다. 가끔 자신이 당신을 인도하라는 계시를 받았다고 이야기하기는 하지만, 그것만 빼면 딱히 방해는 되지 않습니다."
            },
            {
                "type" : "end"
            }
            
        ],

        "rat_encounter" : [
            {
                "type" : "static_line",
                "ent_type" : "npc",
                "speaker" : "rat",
                "text" : "찍찍!"
            },
            {
                "type" : "narration",
                "text" : "쥐가 나타났습니다. 크기는 개만합니다. 이 황무지에서는 흔히 보이는 녀석이죠."
            },
            {
                "type" : "static_line",
                "ent_type" : "pawn",
                "speaker" : "nameless_girl",
                "text" : "쥐가 숨어있었나 보네요. 당신은 우리를 이끌어야 할 몸. 제가 처리하도록 하겠습니다."
            },
            {
                "type" : "narration",
                "text" : "싸울 시간입니다. 소녀에게 지시를 내리십시오!"
            },
            {
                "type" : "narration",
                "text" : "턴은 항상 아군부터 가지고 시작합니다. 현재 턴을 잡은 아군을 클릭하여 행동을 시킬 수 있습니다."
            },
            {
                "type" : "narration",
                "text" : "턴을 잡은 아군을 선택한 상태에선 빈 타일을 클릭해 이동하거나, 적을 클릭해 공격할 수 있습니다. 본인을 한번 더 클릭하면 그 외에도 여러 행동을 수행할 수 있습니다."
            },
            {
                "type" : "narration",
                "text" : "전투를 시작합니다. 쥐를 물리치세요!"
            },
            {
                "type" : "end"
            }
        ]

    
    }
}